crimsy/__init__.py
crimsy/app.py
crimsy/dependencies.py
crimsy/exceptions.py
crimsy/openapi.py
crimsy/params.py
crimsy/router.py
crimsy-0.1.12.dist-info/METADATA
crimsy-0.1.12.dist-info/WHEEL
crimsy-0.1.12.dist-info/licenses/LICENSE
crimsy-0.1.12.dist-info/RECORD
