Metadata-Version: 2.4
Name: crimsy
Version: 0.1.12
Summary: A lightweight web framework for building APIs in Python
License-File: LICENSE
Requires-Python: >=3.11
Requires-Dist: msgspec>=0.19.0
Requires-Dist: python-multipart>=0.0.20
Requires-Dist: starlette>=0.50.0
